seCore/CustomLogging.py
seCore/__init__.py
seCore/compat.py
seCore/filepath.py
seCore/util.py
seCore/win32.py
seVersion/__init__.py
seVersion/_version.py
seVersion/cli.py
seVersion-2024.1.1.dist-info/METADATA
seVersion-2024.1.1.dist-info/WHEEL
seVersion-2024.1.1.dist-info/entry_points.txt
seVersion-2024.1.1.dist-info/top_level.txt
seVersion-2024.1.1.dist-info/RECORD
