Metadata-Version: 2.1
Name: seVersion
Version: 2024.1.1
Summary: CLI to enhance versioning for Python projects
Author-email: "Robert J. DeWilde" <robert.j.dewilde@cyberneticinnovations.com>
License: MIT License
Classifier: License :: OSI Approved :: MIT License
Requires-Python: >=3.7
Requires-Dist: click
Requires-Dist: loguru
Requires-Dist: zope.interface
